{
    "Préface" : {
        "La chasse à cours" : {},
        "La chasse à court" : {},
        "La chasse tout cours" : {}
    },
    "Introduction" : {
        "Environnement & Chasse" : {}, 
        "L'equipment du chasseur" : {},
        "Le bon et le mauvais chasseur" : {}
    },
    "Les forêts de Veilleurandes" : {            
            "Le Garde chasse" : {
                "Le Bas Jardin" : {},
                "La Grande forêt" : {}
                "" : {}
            },
            "La forêt des Sapins" : {},
            "La forêt des Bouleaux" : {}
        },
    "Le bestiaire de Veilleurande":{
        
    }    
}
